win_can_tool/__init__.py
win_can_tool/bus.py
win_can_tool/cli.py
win_can_tool/engine.py
win_can_tool/gui.py
win_can_tool/profiles.py
win_can_tool/version.py
win_can_tool/ics/__init__.py
win_can_tool/ics/__version.py
win_can_tool/ics/hiddenimports.py
win_can_tool/ics/py_neo_device_ex.py
win_can_tool/ics/structures/__init__.py
win_can_tool/ics/structures/a2_b_monitor_settings.py
win_can_tool/ics/structures/a2_b_node_type.py
win_can_tool/ics/structures/a2_btdm_mode.py
win_can_tool/ics/structures/can_settings.py
win_can_tool/ics/structures/canfd_settings.py
win_can_tool/ics/structures/canterm_settings.py
win_can_tool/ics/structures/clock_quality_.py
win_can_tool/ics/structures/cmp_global_data.py
win_can_tool/ics/structures/cmp_network_data.py
win_can_tool/ics/structures/current_ds_.py
win_can_tool/ics/structures/device_feature.py
win_can_tool/ics/structures/disk_settings.py
win_can_tool/ics/structures/e_device_settings_type.py
win_can_tool/ics/structures/e_disk_format.py
win_can_tool/ics/structures/e_disk_layout.py
win_can_tool/ics/structures/e_generic_api_options.py
win_can_tool/ics/structures/e_gptp_port.py
win_can_tool/ics/structures/e_gptp_role.py
win_can_tool/ics/structures/e_plasma_ion_vnet_channel_t.py
win_can_tool/ics/structures/e_uart_port_t.py
win_can_tool/ics/structures/ethernet10_g_settings.py
win_can_tool/ics/structures/ethernet10_t1_s_settings.py
win_can_tool/ics/structures/ethernet10_t1_s_settings_ext.py
win_can_tool/ics/structures/ethernet_network_status_t.py
win_can_tool/ics/structures/ethernet_settings.py
win_can_tool/ics/structures/ethernet_settings2.py
win_can_tool/ics/structures/ew_bms_instance_t.py
win_can_tool/ics/structures/ew_bms_manager_lock_state_t.py
win_can_tool/ics/structures/ew_bms_manager_port_t.py
win_can_tool/ics/structures/extended_response_code.py
win_can_tool/ics/structures/extended_response_generic.py
win_can_tool/ics/structures/fire3_linux_settings.py
win_can_tool/ics/structures/flex_vnet_mode.py
win_can_tool-1.2.29.dist-info/licenses/LICENSE
win_can_tool-1.2.29.dist-info/METADATA
win_can_tool-1.2.29.dist-info/WHEEL
win_can_tool-1.2.29.dist-info/entry_points.txt
win_can_tool-1.2.29.dist-info/top_level.txt
win_can_tool-1.2.29.dist-info/RECORD
