Metadata-Version: 2.4
Name: win_can_tool
Version: 1.2.29
Summary: Windows CAN simulator and testing tool with GUI and CLI.
Author: Kurtis Fafard
License: MIT
Project-URL: Homepage, https://github.com/kfafard/win_can_tool
Project-URL: Source, https://github.com/kfafard/win_can_tool
Project-URL: Issues, https://github.com/kfafard/win_can_tool/issues
Keywords: CAN,J1939,NMEA2000,tractor,simulator,python-can,PyQt6
Classifier: Programming Language :: Python :: 3
Classifier: Programming Language :: Python :: 3.10
Classifier: Programming Language :: Python :: 3.11
Classifier: Programming Language :: Python :: 3.12
Classifier: License :: OSI Approved :: MIT License
Classifier: Operating System :: OS Independent
Classifier: Topic :: Scientific/Engineering
Classifier: Topic :: Software Development :: Testing
Requires-Python: >=3.10
License-File: LICENSE
Requires-Dist: PyQt6
Requires-Dist: python-can
Dynamic: license-file
